README.md
setup.cfg
setup.py
autodiff/__init__.py
autodiff/functions.py
autodiff/optimize.py
autodiff/scalar.py
autodiff/vector.py
autodiff_py.egg-info/PKG-INFO
autodiff_py.egg-info/SOURCES.txt
autodiff_py.egg-info/dependency_links.txt
autodiff_py.egg-info/requires.txt
autodiff_py.egg-info/top_level.txt