Metadata-Version: 2.1
Name: autodiff-py
Version: 1.0
Summary: Automatic Differentiation package
Home-page: https://github.com/cs207FinalProjectGroup/cs207-FinalProject
Author: Ellie Han, Julien Laasri, Brian Lin, Bhaven Patel
License: MIT
Platform: UNKNOWN
Classifier: Development Status :: 5 - Production/Stable
Classifier: Programming Language :: Python :: 3
Classifier: License :: OSI Approved :: MIT License
Classifier: Operating System :: OS Independent
